__init__.py
genifai/__init__.py
genifai/cli.py
genifai/client.py
genifai/config.py
genifai-0.1.0.dist-info/licenses/LICENSE
genifai-0.1.0.dist-info/METADATA
genifai-0.1.0.dist-info/WHEEL
genifai-0.1.0.dist-info/entry_points.txt
genifai-0.1.0.dist-info/top_level.txt
genifai-0.1.0.dist-info/RECORD
