Metadata-Version: 2.4
Name: genifai
Version: 0.1.0
Summary: AI-powered test case generator for C projects
Author-email: dev-x00 <genifai.dev@gmail.com>
License: MIT
Project-URL: Homepage, https://genifai-web.vercel.app
Project-URL: Repository, https://github.com/genifai-dev/genifai-python
Keywords: testing,testcase,ai,code-analysis,c-language,cli
Classifier: Development Status :: 3 - Alpha
Classifier: Intended Audience :: Developers
Classifier: License :: OSI Approved :: MIT License
Classifier: Programming Language :: Python :: 3
Classifier: Programming Language :: Python :: 3.8
Classifier: Programming Language :: Python :: 3.9
Classifier: Programming Language :: Python :: 3.10
Classifier: Programming Language :: Python :: 3.11
Classifier: Programming Language :: Python :: 3.12
Classifier: Topic :: Software Development :: Testing
Classifier: Topic :: Software Development :: Code Generators
Requires-Python: >=3.8
License-File: LICENSE
Requires-Dist: requests>=2.31.0
Requires-Dist: click>=8.1.0
Requires-Dist: rich>=13.0.0
Requires-Dist: pyyaml>=6.0
Requires-Dist: requests-toolbelt>=0.10.0
Provides-Extra: dev
Requires-Dist: pytest>=7.0.0; extra == "dev"
Requires-Dist: black>=23.0.0; extra == "dev"
Dynamic: license-file
